csv_transcriber/__init__.py
csv_transcriber/csv_transcriber.py
csv_transcriber-1.0.dist-info/LICENSE
csv_transcriber-1.0.dist-info/METADATA
csv_transcriber-1.0.dist-info/WHEEL
csv_transcriber-1.0.dist-info/top_level.txt
csv_transcriber-1.0.dist-info/RECORD
